README.md
setup.cfg
setup.py
DemoUnit/__init__.py
DemoUnit.egg-info/PKG-INFO
DemoUnit.egg-info/SOURCES.txt
DemoUnit.egg-info/dependency_links.txt
DemoUnit.egg-info/top_level.txt
DemoUnit/capabilities/__init__.py
DemoUnit/tests/__init__.py